did_webvh/__init__.py
did_webvh/const.py
did_webvh/core/__init__.py
did_webvh/core/date_utils.py
did_webvh/core/did_url.py
did_webvh/core/hash_utils.py
did_webvh/core/loader.py
did_webvh/core/multi_key.py
did_webvh/core/resolver.py
did_webvh/core/state.py
did_webvh/core/tests/test_core_resolver.py
did_webvh/core/tests/test_multi_key.py
did_webvh/core/tests/test_state.py
did_webvh/domain_path.py
did_webvh/history.py
did_webvh/proof.py
did_webvh/provision.py
did_webvh/resolver.py
did_webvh/tests/test_domain_path.py
did_webvh/tests/test_proof.py
did_webvh/tests/test_resolver.py
did_webvh/update.py
did_webvh_jamie_testing-0.2.1.dist-info/LICENSE
did_webvh_jamie_testing-0.2.1.dist-info/METADATA
did_webvh_jamie_testing-0.2.1.dist-info/WHEEL
did_webvh_jamie_testing-0.2.1.dist-info/RECORD
